drfr/.DS_Store
drfr/BasisGenerator.py
drfr/DataSet.py
drfr/DiffusionMap.py
drfr/NoveltyDetector.py
drfr/ReductionModel.py
drfr/RegressionModel.py
drfr/RobustHessianLLE.py
drfr/Run.py
drfr/__init__.py
drfr/setup.py
drfr-0.9.6.dist-info/LICENSE
drfr-0.9.6.dist-info/METADATA
drfr-0.9.6.dist-info/WHEEL
drfr-0.9.6.dist-info/top_level.txt
drfr-0.9.6.dist-info/RECORD
