Metadata-Version: 2.1
Name: drfr
Version: 0.9.6
Summary: A Small Package for Use of Research
Home-page: UNKNOWN
Author: Zhiang Liu
Author-email: me262r@gmail.com
License: UNKNOWN
Platform: UNKNOWN
Classifier: Programming Language :: Python :: 3
Classifier: Operating System :: OS Independent
Classifier: Operating System :: Microsoft :: Windows
Requires-Dist: umap-learn
Requires-Dist: numpy (>=1.13)
Requires-Dist: scipy (>=0.19)
Requires-Dist: scikit-learn (>=0.18)
Requires-Dist: pyod
